assetpipe/__init__.py
assetpipe/cli.py
assetpipe/converters/__init__.py
assetpipe/converters/base.py
assetpipe/converters/fbx.py
assetpipe/converters/gltf.py
assetpipe/converters/obj.py
assetpipe/converters/texture.py
assetpipe/core/__init__.py
assetpipe/core/asset.py
assetpipe/core/config.py
assetpipe/core/pipeline.py
assetpipe/core/watcher.py
assetpipe/optimizers/__init__.py
assetpipe/optimizers/mesh.py
assetpipe/optimizers/texture.py
assetpipe/plugins/__init__.py
assetpipe/utils/__init__.py
assetpipe/utils/notifications.py
assetpipe/utils/reporting.py
assetpipe/validators/__init__.py
assetpipe/validators/base.py
assetpipe/validators/rules.py
assetpipe-0.1.0.dist-info/METADATA
assetpipe-0.1.0.dist-info/WHEEL
assetpipe-0.1.0.dist-info/entry_points.txt
assetpipe-0.1.0.dist-info/licenses/LICENSE
assetpipe-0.1.0.dist-info/RECORD
