Metadata-Version: 2.4
Name: assetpipe
Version: 0.1.0
Summary: Universal Asset Pipeline CLI - Convert, optimize, and validate 3D/2D assets
Project-URL: Homepage, https://github.com/assetpipe/assetpipe
Project-URL: Documentation, https://assetpipe.dev/docs
Project-URL: Repository, https://github.com/assetpipe/assetpipe
Author: AssetPipe Team
License-Expression: MIT
License-File: LICENSE
Keywords: 3d,assets,conversion,gamedev,optimization,pipeline,vfx
Classifier: Development Status :: 4 - Beta
Classifier: Environment :: Console
Classifier: Intended Audience :: Developers
Classifier: License :: OSI Approved :: MIT License
Classifier: Operating System :: OS Independent
Classifier: Programming Language :: Python :: 3.10
Classifier: Programming Language :: Python :: 3.11
Classifier: Programming Language :: Python :: 3.12
Classifier: Topic :: Multimedia :: Graphics :: 3D Modeling
Classifier: Topic :: Multimedia :: Graphics :: Graphics Conversion
Requires-Python: >=3.10
Requires-Dist: httpx>=0.25.0
Requires-Dist: numpy>=1.24.0
Requires-Dist: pillow>=10.0.0
Requires-Dist: pydantic-settings>=2.0.0
Requires-Dist: pydantic>=2.0.0
Requires-Dist: pygltflib>=1.16.0
Requires-Dist: python-json-logger>=2.0.0
Requires-Dist: pyyaml>=6.0
Requires-Dist: rich>=13.0.0
Requires-Dist: trimesh>=4.0.0
Requires-Dist: typer[all]>=0.9.0
Requires-Dist: watchdog>=3.0.0
Provides-Extra: dev
Requires-Dist: black>=23.0.0; extra == 'dev'
Requires-Dist: mypy>=1.0.0; extra == 'dev'
Requires-Dist: pre-commit>=3.0.0; extra == 'dev'
Requires-Dist: pytest-asyncio>=0.21.0; extra == 'dev'
Requires-Dist: pytest-cov>=4.0.0; extra == 'dev'
Requires-Dist: pytest>=7.0.0; extra == 'dev'
Requires-Dist: ruff>=0.1.0; extra == 'dev'
Provides-Extra: fbx
Requires-Dist: fbx>=2020.0.0; extra == 'fbx'
